fastAutoTest/__init__.py
fastAutoTest/core/__init__.py
fastAutoTest/core/common/__init__.py
fastAutoTest/core/common/errormsgmanager.py
fastAutoTest/core/common/command/__init__.py
fastAutoTest/core/common/command/commandProcessor.py
fastAutoTest/core/common/command/jsonConcat.py
fastAutoTest/core/common/network/__init__.py
fastAutoTest/core/common/network/shortLiveWebSocket.py
fastAutoTest/core/common/network/websocketdatatransfer.py
fastAutoTest/core/h5/__init__.py
fastAutoTest/core/h5/h5CommandManager.py
fastAutoTest/core/h5/h5Engine.py
fastAutoTest/core/h5/h5PageOperator.py
fastAutoTest/core/h5/h5UserAPI.py
fastAutoTest/core/h5/h5WebSocketDebugUrlFetcher.py
fastAutoTest/core/qq/__init__.py
fastAutoTest/core/qq/qqEngine.py
fastAutoTest/core/qq/qqWebSocketDebugUrlFetcher.py
fastAutoTest/core/wx/__init__.py
fastAutoTest/core/wx/wxCommandManager.py
fastAutoTest/core/wx/wxEngine.py
fastAutoTest/core/wx/wxPageOperator.py
fastAutoTest/core/wx/wxUserAPI.py
fastAutoTest/core/wx/wxWebSocketDebugUrlFetcher.py
fastAutoTest/core/wx/apk/inputPlug.apk
fastAutoTest/utils/__init__.py
fastAutoTest/utils/adbHelper.py
fastAutoTest/utils/atomicinteger.py
fastAutoTest/utils/commandHelper.py
fastAutoTest/utils/common.py
fastAutoTest/utils/constant.py
fastAutoTest/utils/logger.py
fastAutoTest/utils/singlethreadexecutor.py
fastAutoTest/utils/vmhook.py
fastAutoTest_dev-2.2.4.dist-info/METADATA
fastAutoTest_dev-2.2.4.dist-info/RECORD
fastAutoTest_dev-2.2.4.dist-info/WHEEL
fastAutoTest_dev-2.2.4.dist-info/top_level.txt
sample/H5Demo.py
sample/QQDemo.py
sample/XcqDemo.py
sample/__init__.py
